README.rst
setup.py
django_addons/__init__.py
django_addons/addon_config.py
django_addons/exceptions.py
django_addons/settings.py
django_addons/urls.py
django_addons/utils.py
django_addons.egg-info/PKG-INFO
django_addons.egg-info/SOURCES.txt
django_addons.egg-info/dependency_links.txt
django_addons.egg-info/not-zip-safe
django_addons.egg-info/requires.txt
django_addons.egg-info/top_level.txt